pygeom/__init__.py
pygeom/axes.py
pygeom/ellipse.py
pygeom/line.py
pygeom/point.py
pygeom/polygon.py
pygeom/rectangle.py
pygeom/segment.py
pygeom/triangle.py
pygeom/util.py
pygeom/vector.py
pyGeom2D-0.1.2.dist-info/LICENSE
pyGeom2D-0.1.2.dist-info/METADATA
pyGeom2D-0.1.2.dist-info/WHEEL
pyGeom2D-0.1.2.dist-info/top_level.txt
pyGeom2D-0.1.2.dist-info/RECORD
