Metadata-Version: 2.1
Name: pyGeom2D
Version: 0.1.2
Summary: A package for 2D geometry in Python
Home-page: https://github.com/NaysanSaran/pyGeom2D.git
Author: Naysan Saran
Author-email: naysan.saran@gmail.com
License: MIT
Platform: UNKNOWN
Classifier: Programming Language :: Python :: 3
Classifier: License :: OSI Approved :: MIT License
Classifier: Operating System :: OS Independent
Requires-Python: >=3.6
Requires-Dist: matplotlib
Requires-Dist: numpy
Requires-Dist: scipy
